klay_beam/__init__.py
klay_beam/path.py
klay_beam/py.typed
klay_beam/run_cuda_test.py
klay_beam/run_example.py
klay_beam/torch_transforms.py
klay_beam/torch_utils.py
klay_beam/transforms.py
klay_beam/utils.py
klay_beam-0.14.6.dist-info/licenses/LICENSE
klay_beam-0.14.6.dist-info/METADATA
klay_beam-0.14.6.dist-info/WHEEL
klay_beam-0.14.6.dist-info/top_level.txt
klay_beam-0.14.6.dist-info/RECORD
