Metadata-Version: 2.4
Name: klay-beam
Version: 0.14.6
Summary: Toolkit for massively parallel audio processing via Apache Beam
License:  The MIT License (MIT)
Requires-Python: >=3.9
License-File: LICENSE
Requires-Dist: av
Requires-Dist: apache-beam[gcp]==2.64
Requires-Dist: boto3==1.35
Requires-Dist: conda-lock>=3
Requires-Dist: dill<0.3.2,>=0.3.1.1
Requires-Dist: pydub==0.25.1
Requires-Dist: soundfile>=0.13.0
Requires-Dist: librosa>=0.10
Provides-Extra: code-style
Requires-Dist: black==24.10; extra == "code-style"
Requires-Dist: flake8==7.1; extra == "code-style"
Provides-Extra: tests
Requires-Dist: pytest; extra == "tests"
Requires-Dist: scipy; extra == "tests"
Provides-Extra: type-check
Requires-Dist: mypy==1.14; extra == "type-check"
Requires-Dist: pydantic==2.10; extra == "type-check"
Requires-Dist: types-setuptools; extra == "type-check"
Provides-Extra: pytorch
Requires-Dist: torchaudio>=2; extra == "pytorch"
Requires-Dist: torch>=2; extra == "pytorch"
Dynamic: license-file
